AUTHORS
ChangeLog
README.rst
requirements.txt
setup.cfg
setup.py
django_image_proxy.egg-info/PKG-INFO
django_image_proxy.egg-info/SOURCES.txt
django_image_proxy.egg-info/dependency_links.txt
django_image_proxy.egg-info/not-zip-safe
django_image_proxy.egg-info/pbr.json
django_image_proxy.egg-info/requires.txt
django_image_proxy.egg-info/top_level.txt
image_proxy/__init__.py
image_proxy/processors.py
image_proxy/urls.py
image_proxy/views.py
image_proxy/templates/image_proxy/_image_preview.html
image_proxy/templates/image_proxy/image_preview.html
image_proxy/templatetags/__init__.py
image_proxy/templatetags/proxy_thumbnail.py
image_proxy/templatetags/thumbnail.py